{
   "type": "recipe",
   "effort": 3,
   "work_units": 1,
   "recipe_name": "i18n(stonehearth:jobs.cook.recipes.sheep_feed_recipe.recipe_name)",
   "description": "i18n(stonehearth:jobs.cook.recipes.sheep_feed_recipe.description)",
   "flavor": "",
   "portrait": "/stonehearth/entities/food/sheep_feed/sheep_feed.png",
   "workshop": "stonehearth:cook:mill",
   "level_requirement": 0,
   "ingredients": [
      {
         "material": "thatch resource",
         "count": 3
      }
   ],
   "produces": [
      {
         "item": "stonehearth:food:sheep_feed"
      }
   ]
}
